malls/__init__.py
malls/__main__.py
malls/mal_lsp.py
malls/lsp/classes.py
malls/lsp/enums.py
malls/lsp/fsm.py
malls/lsp/models.py
malls/lsp/utils.py
malls/ts/utils.py
mal_language_server-0.1.0.dist-info/METADATA
mal_language_server-0.1.0.dist-info/WHEEL
mal_language_server-0.1.0.dist-info/entry_points.txt
mal_language_server-0.1.0.dist-info/RECORD
