Metadata-Version: 2.4
Name: mal-language-server
Version: 0.1.0
Summary: Language server for MAL
Project-URL: github, https://github.com/mal-lang/mal-ls
Author-email: Tobiky <me@tobiky.dev>
Requires-Python: >=3.11
Requires-Dist: pydantic>=2.11.7
Requires-Dist: python-lsp-jsonrpc>=1.1.2
Requires-Dist: tree-sitter
Requires-Dist: tree-sitter-mal
Requires-Dist: uritools>=5.0.0
